{
    "AI": {
        "data": {
            "sector": "Technology",
            "industry": "Software - Infrastructure",
            "pe": 0,
            "peg": 0,
            "debt_to_equity": 0.08,
            "description": "C3.ai, Inc. operates as an enterprise artificial intelligence application software company. The company offers C3 agentic AI platform, an application development and runtime environment that enables c..."
        },
        "updated_at": "2026-06-16T18:01:00.486050"
    },
    "CC": {
        "data": {
            "sector": "Basic Materials",
            "industry": "Specialty Chemicals",
            "pe": 0,
            "peg": 1.6,
            "debt_to_equity": 20.34,
            "description": "The Chemours Company provides performance chemicals in North America, the Asia Pacific, Europe, the Middle East, Africa, and Latin America. The company operates through three segments: Thermal & Speci..."
        },
        "updated_at": "2026-06-16T18:01:24.206275"
    },
    "CXAI": {
        "data": {
            "sector": "Technology",
            "industry": "Software - Application",
            "pe": 0,
            "peg": 0,
            "debt_to_equity": 0.69,
            "description": "CXApp Inc. provides experience solutions and delivering enterprise-grade software in the United States, Canada, and the Philippines. It offers CXAI Platform, which provides a comprehensive suite of to..."
        },
        "updated_at": "2026-06-16T18:01:51.717463"
    },
    "BX": {
        "data": {
            "sector": "Financial Services",
            "industry": "Asset Management",
            "pe": 32.82,
            "peg": 2.08,
            "debt_to_equity": 0.72,
            "description": "Blackstone Inc. is an alternative asset management firm specializing in private equity, venture capital, real estate, hedge fund solutions, credit, secondary funds of funds, public debt and equity and..."
        },
        "updated_at": "2026-06-16T18:02:25.235122"
    },
    "GOOGL": {
        "data": {
            "sector": "Communication Services",
            "industry": "Internet Content & Information",
            "pe": 28.31,
            "peg": 1.42,
            "debt_to_equity": 0.2,
            "description": "Alphabet Inc. offers various products and platforms in the United States, Europe, the Middle East, Africa, the Asia-Pacific, Canada, and Latin America. It operates through Google Services, Google Clou..."
        },
        "updated_at": "2026-06-16T18:02:50.845829"
    },
    "INTC": {
        "data": {
            "sector": "Technology",
            "industry": "Semiconductors",
            "pe": 0,
            "peg": 1.36,
            "debt_to_equity": 0.36,
            "description": "Intel Corporation designs, develops, manufactures, markets, sells, and services computing and related end products and services in the United States, Ireland, Israel, and internationally. It operates ..."
        },
        "updated_at": "2026-06-16T18:03:17.344931"
    },
    "VT": {
        "data": {
            "sector": "Unknown",
            "industry": "Unknown",
            "pe": 23.44,
            "peg": 0,
            "debt_to_equity": 0,
            "description": "The fund employs an indexing investment approach designed to track the performance of the FTSE Global All Cap Index. It invests by sampling the target index, meaning that it holds a range of securitie..."
        },
        "updated_at": "2026-06-16T18:03:47.925973"
    },
    "NOK": {
        "data": {
            "sector": "Technology",
            "industry": "Communication Equipment",
            "pe": 86.72,
            "peg": 1.43,
            "debt_to_equity": 0.16,
            "description": "Nokia Oyj, together with its subsidiaries, provides mobile, fixed, and cloud network solutions in North and Latin America, Greater China, India, Asia Pacific, Europe, the Middle East, and Africa. It o..."
        },
        "updated_at": "2026-06-16T18:04:10.850218"
    }
}